{
  "ServerOn": "False",
  "MessageServerFalse": "",
  "Version": "1.8Fix5",
  "gamesizeOriginal": "-",
  "gamesizeOriginalFix": "-",
  "gamesizeENBLow": "-",
  "gamesizeENBSetting": "-",
  "gamesizeENBHigh": "-",
  "ASIC": "999",
  "CSC": "999",
  "LUAC": "999",
  "CBURLLIST": "modloader,false|modloader.asi,false|cleo,false|cleo.asi,false|moonloader,false|moonloader.asi,false",
  "FFC": "-1",
  "UpdateWithLink": "http://api.samp-legend.net/launcher/LegendLauncherUpdate.tmp",
  "LUpdateWithLink": "http://api.samp-legend.net/launcher/LegendUpdateFileReplace.tmp",
  "PIC": "https://img2.imgbiz.com/imgbiz/CB.png"
}
